<?xml version="1.0" encoding="utf-8" ?>
<Defs>
	<ThingDef ParentName="VFEPD_ColourableFurnitureBase">
		<defName>VFEPD_MopBucket</defName>
		<label>mop bucket</label>
		<description>A sterile mop bucket. Ideal for a mop.</description>
		<graphicData>
			<texPath>Things/Building/KitchenProps/MopBucket/MopBucket</texPath>
			<graphicClass>Graphic_Single</graphicClass>
			<drawSize>(2,2)</drawSize>
			<shaderType>CutoutComplex</shaderType>
			<color>(255,228,67)</color>
			<shadowData>
				<volume>(0.55, 0.30, 0.40)</volume>
			</shadowData>
		</graphicData>
		<altitudeLayer>Building</altitudeLayer>
		<rotatable>false</rotatable>
		<passability>PassThroughOnly</passability>
		<fillPercent>0.3</fillPercent>
		<statBases>
			<MaxHitPoints>20</MaxHitPoints>
			<WorkToBuild>0</WorkToBuild>
			<Mass>5</Mass>
			<Flammability>0.5</Flammability>
		</statBases>
		<size>(1,1)</size>
		<uiIconScale>1</uiIconScale>
		<building>
			<isInert>true</isInert>
		</building>
	</ThingDef>
	<ThingDef ParentName="VFEPD_ColourableFurnitureBase">
		<defName>VFEPD_BrewingBarrel</defName>
		<label>brewing barrel</label>
		<description>A large, empty brewing barrel.</description>
		<graphicData>
			<texPath>Things/Building/KitchenProps/BrewingBarrel</texPath>
			<graphicClass>Graphic_Random</graphicClass>
			<drawSize>(1,1)</drawSize>
			<shaderType>CutoutComplex</shaderType>
			<color>(255,196,164)</color>
			<shadowData>
				<volume>(0.55, 0.30, 0.40)</volume>
			</shadowData>
		</graphicData>
		<altitudeLayer>Building</altitudeLayer>
		<rotatable>false</rotatable>
		<passability>PassThroughOnly</passability>
		<fillPercent>0.3</fillPercent>
		<pathCost>14</pathCost>
		<statBases>
			<MaxHitPoints>100</MaxHitPoints>
			<WorkToBuild>0</WorkToBuild>
			<Mass>5</Mass>
			<Flammability>1</Flammability>
		</statBases>
		<size>(1,1)</size>
		<uiIconScale>1</uiIconScale>
		<building>
			<isInert>true</isInert>
		</building>
	</ThingDef>
	<ThingDef ParentName="VFEPD_NonColourableFurnitureBase">
		<defName>VFEPD_Cooker</defName>
		<label>cooker</label>
		<description>A cooker unit.</description>
		<graphicData>
			<texPath>Things/Building/KitchenProps/Cooker/Cooker</texPath>
			<graphicClass>Graphic_Multi</graphicClass>
			<drawSize>(1.1,1.1)</drawSize>
			<shadowData>
				<volume>(0.55, 0.30, 0.40)</volume>
			</shadowData>
		</graphicData>
		<altitudeLayer>Building</altitudeLayer>
		<rotatable>true</rotatable>
		<defaultPlacingRot>South</defaultPlacingRot>
		<passability>PassThroughOnly</passability>
		<fillPercent>0.3</fillPercent>
		<pathCost>42</pathCost>
		<statBases>
			<MaxHitPoints>60</MaxHitPoints>
			<WorkToBuild>0</WorkToBuild>
			<Mass>15</Mass>
			<Flammability>0</Flammability>
		</statBases>
		<size>(1,1)</size>
		<uiIconScale>1</uiIconScale>
		<building>
			<isInert>true</isInert>
		</building>
	</ThingDef>
	<ThingDef ParentName="VFEPD_NonColourableFurnitureBase">
		<defName>VFEPD_Microwave</defName>
		<label>microwave</label>
		<description>A tabletop microwave device.</description>
		<graphicData>
			<texPath>Things/Building/KitchenProps/Microwave/Microwave</texPath>
			<graphicClass>Graphic_Multi</graphicClass>
			<drawSize>(1.5,1.5)</drawSize>
			<shadowData>
				<volume>(0.55, 0.30, 0.40)</volume>
			</shadowData>
		</graphicData>
		<altitudeLayer>Building</altitudeLayer>
		<passability>PassThroughOnly</passability>
		<fillPercent>0.3</fillPercent>
		<rotatable>true</rotatable>
		<pathCost>42</pathCost>
		<defaultPlacingRot>South</defaultPlacingRot>
		<statBases>
			<MaxHitPoints>60</MaxHitPoints>
			<WorkToBuild>0</WorkToBuild>
			<Mass>15</Mass>
			<Flammability>0</Flammability>
		</statBases>
		<size>(1,1)</size>
		<uiIconScale>1</uiIconScale>
		<building>
			<isInert>true</isInert>
		</building>
	</ThingDef>
	<ThingDef ParentName="VFEPD_NonColourableFurnitureBase">
		<defName>VFEPD_Oven</defName>
		<label>oven</label>
		<description>A large oven.</description>
		<graphicData>
			<texPath>Things/Building/KitchenProps/Oven/Oven</texPath>
			<graphicClass>Graphic_Multi</graphicClass>
			<drawSize>(1.5,1.5)</drawSize>
			<shadowData>
				<volume>(0.55, 0.30, 0.40)</volume>
			</shadowData>
		</graphicData>
		<altitudeLayer>Building</altitudeLayer>
		<passability>Impassable</passability>
		<rotatable>true</rotatable>
		<pathCost>42</pathCost>
		<defaultPlacingRot>South</defaultPlacingRot>
		<fillPercent>0.5</fillPercent>
		<statBases>
			<MaxHitPoints>60</MaxHitPoints>
			<WorkToBuild>0</WorkToBuild>
			<Mass>25</Mass>
			<Flammability>0</Flammability>
		</statBases>
		<size>(1,1)</size>
		<uiIconScale>1</uiIconScale>
		<building>
			<isInert>true</isInert>
		</building>
	</ThingDef>
	<ThingDef ParentName="VFEPD_ColourableFurnitureBase">
		<defName>VFEPD_Fridge</defName>
		<label>fridge</label>
		<description>A large fridge with an in-built freezer.</description>
		<graphicData>
			<texPath>Things/Building/KitchenProps/Fridge/KitchenFridge</texPath>
			<graphicClass>Graphic_Multi</graphicClass>
			<drawSize>(3,3)</drawSize>
			<shadowData>
				<volume>(0.55, 0.30, 0.40)</volume>
			</shadowData>
			<color>(157,157,157)</color>
			<shaderType>CutoutComplex</shaderType>
		</graphicData>
		<altitudeLayer>Building</altitudeLayer>
		<passability>Impassable</passability>
		<rotatable>true</rotatable>
		<defaultPlacingRot>South</defaultPlacingRot>
		<fillPercent>0.5</fillPercent>
		<statBases>
			<MaxHitPoints>80</MaxHitPoints>
			<WorkToBuild>0</WorkToBuild>
			<Mass>25</Mass>
			<Flammability>0</Flammability>
		</statBases>
		<size>(1,1)</size>
		<uiIconScale>1</uiIconScale>
		<building>
			<isInert>true</isInert>
		</building>
	</ThingDef>
	<ThingDef ParentName="VFEPD_NonColourableFurnitureBase">
		<defName>VFEPD_WaterDispenser</defName>
		<label>water dispenser</label>
		<description>A large, standing fresh water dispenser.</description>
		<graphicData>
			<texPath>Things/Building/KitchenProps/WaterDispenser/WaterDispenser</texPath>
			<graphicClass>Graphic_Multi</graphicClass>
			<drawSize>(2.5,2.5)</drawSize>
			<shadowData>
				<volume>(0.55, 0.30, 0.40)</volume>
			</shadowData>
		</graphicData>
		<altitudeLayer>Building</altitudeLayer>
		<pathCost>42</pathCost>
		<passability>PassThroughOnly</passability>
		<rotatable>true</rotatable>
		<defaultPlacingRot>South</defaultPlacingRot>
		<fillPercent>0.3</fillPercent>
		<statBases>
			<MaxHitPoints>60</MaxHitPoints>
			<WorkToBuild>0</WorkToBuild>
			<Mass>10</Mass>
			<Flammability>0</Flammability>
		</statBases>
		<size>(1,1)</size>
		<uiIconScale>1</uiIconScale>
		<building>
			<isInert>true</isInert>
		</building>
	</ThingDef>
	<ThingDef ParentName="VFEPD_NonColourableFurnitureBase">
		<defName>VFEPD_FoodTrolley</defName>
		<label>food trolley</label>
		<description>A four wheeled trolley for empty plates and food trays.</description>
		<graphicData>
			<texPath>Things/Building/KitchenProps/FoodTrolley</texPath>
			<graphicClass>Graphic_Random</graphicClass>
			<drawSize>(1.2,1.2)</drawSize>
			<shadowData>
				<volume>(0.55, 0.30, 0.40)</volume>
			</shadowData>
		</graphicData>
		<altitudeLayer>Building</altitudeLayer>
		<rotatable>false</rotatable>
		<passability>PassThroughOnly</passability>
		<fillPercent>0.1</fillPercent>
		<statBases>
			<MaxHitPoints>20</MaxHitPoints>
			<WorkToBuild>0</WorkToBuild>
			<Mass>5</Mass>
			<Flammability>0</Flammability>
		</statBases>
		<size>(1,1)</size>
		<uiIconScale>1</uiIconScale>
		<building>
			<isInert>true</isInert>
		</building>
	</ThingDef>
	<ThingDef ParentName="VFEPD_ColourableFurnitureBase">
		<defName>VFEPD_KitchenSurface</defName>
		<label>kitchen surface</label>
		<description>A simple kitchen surface with a cutting board.</description>
		<graphicData>
			<texPath>Things/Building/KitchenProps/KitchenSurface/KitchenSurface</texPath>
			<graphicClass>Graphic_Multi</graphicClass>
			<drawSize>(3.5,1.5)</drawSize>
			<shadowData>
				<volume>(2.5, 0.4, 0.40)</volume>
			</shadowData>
			<color>(157,157,157)</color>
			<shaderType>CutoutComplex</shaderType>
		</graphicData>
		<altitudeLayer>Building</altitudeLayer>
		<passability>PassThroughOnly</passability>
		<fillPercent>0.3</fillPercent>
		<pathCost>42</pathCost>
		<rotatable>true</rotatable>
		<defaultPlacingRot>South</defaultPlacingRot>
		<statBases>
			<MaxHitPoints>180</MaxHitPoints>
			<WorkToBuild>0</WorkToBuild>
			<Mass>15</Mass>
			<Flammability>0</Flammability>
		</statBases>
		<size>(3,1)</size>
		<uiIconScale>1</uiIconScale>
		<building>
			<isInert>true</isInert>
		</building>
	</ThingDef>
	<ThingDef ParentName="VFEPD_ColourableFurnitureBase">
		<defName>VFEPD_KitchenSurfaceEmpty</defName>
		<label>kitchen surface, empty</label>
		<description>A simple kitchen surface.</description>
		<graphicData>
			<texPath>Things/Building/KitchenProps/KitchenSurfaceEmpty/KitchenSurfaceEmpty</texPath>
			<graphicClass>Graphic_Multi</graphicClass>
			<drawSize>(3.5,1.5)</drawSize>
			<shadowData>
				<volume>(2.5, 0.4, 0.40)</volume>
			</shadowData>
			<color>(157,157,157)</color>
			
		</graphicData>
		<altitudeLayer>Building</altitudeLayer>
		<passability>PassThroughOnly</passability>
		<fillPercent>0.3</fillPercent>
		<pathCost>42</pathCost>
		<rotatable>true</rotatable>
		<defaultPlacingRot>South</defaultPlacingRot>
		<statBases>
			<MaxHitPoints>180</MaxHitPoints>
			<WorkToBuild>0</WorkToBuild>
			<Mass>15</Mass>
			<Flammability>0</Flammability>
		</statBases>
		<size>(3,1)</size>
		<uiIconScale>1</uiIconScale>
		<building>
			<isInert>true</isInert>
		</building>
	</ThingDef>
	<ThingDef ParentName="VFEPD_ColourableFurnitureBase">
		<defName>VFEPD_KitchenSink</defName>
		<label>kitchen sink</label>
		<description>A long kitchen sink.</description>
		<graphicData>
			<texPath>Things/Building/KitchenProps/KitchenSink/KitchenSink</texPath>
			<graphicClass>Graphic_Multi</graphicClass>
			<drawSize>(3.5,1.5)</drawSize>
			<shadowData>
				<volume>(2.5, 0.4, 0.40)</volume>
			</shadowData>
			<color>(157,157,157)</color>
			<shaderType>CutoutComplex</shaderType>
		</graphicData>
		<altitudeLayer>Building</altitudeLayer>
		<passability>PassThroughOnly</passability>
		<fillPercent>0.3</fillPercent>
		<pathCost>42</pathCost>
		<rotatable>true</rotatable>
		<defaultPlacingRot>South</defaultPlacingRot>
		<statBases>
			<MaxHitPoints>180</MaxHitPoints>
			<WorkToBuild>0</WorkToBuild>
			<Mass>15</Mass>
			<Flammability>0</Flammability>
		</statBases>
		<size>(3,1)</size>
		<uiIconScale>1</uiIconScale>
		<building>
			<isInert>true</isInert>
		</building>
	</ThingDef>
	<ThingDef ParentName="VFEPD_NonColourableFurnitureBase">
		<defName>VFEPD_WineRack</defName>
		<label>wine rack</label>
		<description>A civilised wine storage rack.</description>
		<graphicData>
			<texPath>Things/Building/KitchenProps/WineRack/WineRack</texPath>
			<graphicClass>Graphic_Multi</graphicClass>
			<drawSize>(2,2)</drawSize>
			<shadowData>
				<volume>(0.55, 0.30, 0.40)</volume>
			</shadowData>
		</graphicData>
		<altitudeLayer>Building</altitudeLayer>
		<rotatable>true</rotatable>
		<defaultPlacingRot>South</defaultPlacingRot>
		<passability>PassThroughOnly</passability>
		<pathCost>14</pathCost>
		<fillPercent>0.3</fillPercent>
		<statBases>
			<MaxHitPoints>50</MaxHitPoints>
			<WorkToBuild>0</WorkToBuild>
			<Mass>15</Mass>
			<Flammability>1</Flammability>
		</statBases>
		<size>(1,1)</size>
		<uiIconScale>1</uiIconScale>
		<building>
			<isInert>true</isInert>
		</building>
	</ThingDef>
	<ThingDef ParentName="VFEPD_NonColourableFurnitureBase">
		<defName>VFEPD_CookingAppliances</defName>
		<label>pot</label>
		<description>A large pot.</description>
		<graphicData>
			<texPath>Things/Building/KitchenProps/CookingAppliances/Pot</texPath>
			<graphicClass>Graphic_Single</graphicClass>
			<drawSize>(1,1)</drawSize>
		</graphicData>
		<rotatable>false</rotatable>
		<altitudeLayer>Item</altitudeLayer>
		<passability>PassThroughOnly</passability>
		<clearBuildingArea>false</clearBuildingArea>
		<fillPercent>0.1</fillPercent>
		<building>
			<isEdifice>false</isEdifice>
		</building>
		<statBases>
			<MaxHitPoints>10</MaxHitPoints>
			<WorkToBuild>0</WorkToBuild>
			<Mass>5</Mass>
			<Flammability>0.2</Flammability>
		</statBases>
		<size>(1,1)</size>
		<uiIconScale>1</uiIconScale>
	</ThingDef>
	<ThingDef ParentName="VFEPD_NonColourableFurnitureBase">
		<defName>VFEPD_CookingPan</defName>
		<label>pan</label>
		<description>A large pan.</description>
		<graphicData>
			<texPath>Things/Building/KitchenProps/CookingAppliances/Pan</texPath>
			<graphicClass>Graphic_Single</graphicClass>
			<drawSize>(1,1)</drawSize>
		</graphicData>
		<rotatable>false</rotatable>
		<altitudeLayer>Item</altitudeLayer>
		<passability>PassThroughOnly</passability>
		<clearBuildingArea>false</clearBuildingArea>
		<fillPercent>0.1</fillPercent>
		<building>
			<isEdifice>false</isEdifice>
		</building>
		<statBases>
			<MaxHitPoints>10</MaxHitPoints>
			<WorkToBuild>0</WorkToBuild>
			<Mass>5</Mass>
			<Flammability>0.2</Flammability>
		</statBases>
		<size>(1,1)</size>
		<uiIconScale>1</uiIconScale>
	</ThingDef>
	<ThingDef ParentName="VFEPD_NonColourableFurnitureBase">
		<defName>VFEPD_CuttingBoard</defName>
		<label>cutting board</label>
		<description>A wooden cutting board.</description>
		<graphicData>
			<texPath>Things/Building/KitchenProps/CuttingBoard/CuttingBoard</texPath>
			<graphicClass>Graphic_Multi</graphicClass>
			<drawSize>(1,1)</drawSize>
		</graphicData>
		<rotatable>true</rotatable>
		<defaultPlacingRot>South</defaultPlacingRot>
		<altitudeLayer>BuildingOnTop</altitudeLayer>
		<passability>PassThroughOnly</passability>
		<clearBuildingArea>false</clearBuildingArea>
		<fillPercent>0.1</fillPercent>
		<building>
			<isEdifice>false</isEdifice>
		</building>
		<statBases>
			<MaxHitPoints>10</MaxHitPoints>
			<WorkToBuild>0</WorkToBuild>
			<Mass>5</Mass>
			<Flammability>0.2</Flammability>
		</statBases>
		<size>(1,1)</size>
		<uiIconScale>1</uiIconScale>
	</ThingDef>
	<ThingDef ParentName="VFEPD_NonColourableFurnitureBase">
		<defName>VFEPD_Knives</defName>
		<label>knives</label>
		<description>A set of cooking knives.</description>
		<graphicData>
			<texPath>Things/Building/KitchenProps/Knives/Knives</texPath>
			<graphicClass>Graphic_Multi</graphicClass>
			<drawSize>(1,1)</drawSize>
		</graphicData>
		<rotatable>true</rotatable>
		<defaultPlacingRot>South</defaultPlacingRot>
		<altitudeLayer>Item</altitudeLayer>
		<passability>PassThroughOnly</passability>
		<clearBuildingArea>false</clearBuildingArea>
		<fillPercent>0.1</fillPercent>
		<building>
			<isEdifice>false</isEdifice>
		</building>
		<statBases>
			<MaxHitPoints>10</MaxHitPoints>
			<WorkToBuild>0</WorkToBuild>
			<Mass>5</Mass>
			<Flammability>0.2</Flammability>
		</statBases>
		<size>(1,1)</size>
		<uiIconScale>1</uiIconScale>
	</ThingDef>
	<ThingDef ParentName="VFEPD_NonColourableFurnitureBase">
		<defName>VFEPD_DinnerSet</defName>
		<label>dinner set</label>
		<description>A simple dinner set containing all the required utensils.</description>
		<graphicData>
			<texPath>Things/Building/KitchenProps/DinnerSet/DinnerSet</texPath>
			<graphicClass>Graphic_Multi</graphicClass>
			<drawSize>(1,1)</drawSize>
		</graphicData>
		<rotatable>true</rotatable>
		<defaultPlacingRot>South</defaultPlacingRot>
		<altitudeLayer>Item</altitudeLayer>
		<passability>PassThroughOnly</passability>
		<clearBuildingArea>false</clearBuildingArea>
		<fillPercent>0.1</fillPercent>
		<building>
			<isEdifice>false</isEdifice>
		</building>
		<statBases>
			<MaxHitPoints>10</MaxHitPoints>
			<WorkToBuild>0</WorkToBuild>
			<Mass>5</Mass>
			<Flammability>0.2</Flammability>
		</statBases>
		<size>(1,1)</size>
		<uiIconScale>1</uiIconScale>
	</ThingDef>
	<ThingDef ParentName="VFEPD_NonColourableFurnitureBase">
		<defName>VFEPD_Spices</defName>
		<label>spices</label>
		<description>A wide assortment of different spices</description>
		<graphicData>
			<texPath>Things/Building/KitchenProps/Spices</texPath>
			<graphicClass>Graphic_Random</graphicClass>
			<drawSize>(1,1)</drawSize>
		</graphicData>
		<rotatable>false</rotatable>
		<altitudeLayer>Item</altitudeLayer>
		<passability>PassThroughOnly</passability>
		<clearBuildingArea>false</clearBuildingArea>
		<fillPercent>0.1</fillPercent>
		<building>
			<isEdifice>false</isEdifice>
		</building>
		<statBases>
			<MaxHitPoints>10</MaxHitPoints>
			<WorkToBuild>0</WorkToBuild>
			<Mass>5</Mass>
			<Flammability>0.2</Flammability>
		</statBases>
		<size>(1,1)</size>
		<uiIconScale>1</uiIconScale>
	</ThingDef>
</Defs>
